[
    {
        "rows": [
            [
                {
                    "name": "name"
                },
                {
                    "name": "status"
                }
            ],
            [
                {
                    "name": "from"
                },
                {
                    "name": "to"
                }
            ],
            [
                {
                    "name": "lead"
                },
                {
                    "name": "contact"
                }
            ],
            [
                {
                    "name": "source"
                },
                false
            ],
            [
                {
                    "name": "direction"
                },
                {
                    "name": "messageId"
                }
            ],
            [
                {
                    "name": "body"
                }
            ],
            [
                {
                    "name": "description"
                }
            ]
        ],
        "style": "default",
        "label": ""
    }
]